ALU/alu.v
// unsigned alu
module alu (
    // input
    input wire       rst_n,
    input wire       CLK,
    input wire       en,
    input wire [7:0] A,
    input wire [7:0] B,
    input wire [2:0] OP,
    // output
    output reg [15:0] result
);

localparam ADD     = 3'b000;
localparam MUL     = 3'b001;
localparam AND     = 3'b010;
localparam OR      = 3'b011;
localparam XOR     = 3'b100;
localparam NOTA    = 3'b101;


always @(posedge CLK) begin
    if (!rst_n) begin
        result <= 16'b0;
    end
    else if (en) begin
        if (OP == ADD) begin
            result <= A + B;
        end
        else if (OP == MUL) begin
            result <= A * B;
        end
        else if (OP == AND) begin
            result <= A & B;
        end
        else if (OP == OR) begin
            result <= A | B;
        end
        else if (OP == XOR) begin
            result <= A ^ B;
        end
        else if (OP == NOTA) begin
            result <= {{8{1'b0}},~A};
        end
    end
end

initial begin
	$dumpfile("alu.vcd");
	$dumpvars(1,alu);
end

endmodule

ALU/alu.vcd
$date
	Sat Jul 20 02:02:15 2024
$end
$version
	Icarus Verilog
$end
$timescale
	1ps
$end
$scope module alu $end
$var wire 8 ! A [7:0] $end
$var wire 8 " B [7:0] $end
$var wire 1 # CLK $end
$var wire 3 $ OP [2:0] $end
$var wire 1 % en $end
$var wire 1 & rst_n $end
$var reg 16 ' result [15:0] $end
$upscope $end
$enddefinitions $end
#0
$dumpvars
bx '
z&
z%
bz $
1#
bz "
bz !
$end
#1000
b0 $
b0 "
b0 !
0%
0&
0#
#2000
b0 '
1#
#3000
1%
1&
0#
#4000
1#
#5000
b11010 "
b10001111 !
0#
#6000
b10101001 '
1#
#7000
0#
#8000
1#
#9000
b1 $
b111000 "
b10110101 !
0#
#10000
b10011110011000 '
1#
#11000
0#
#12000
1#
#13000
b1011101 "
b11111001 !
0#
#14000
b101101001110101 '
1#
#15000
0#
#16000
1#
#17000
b1000110 "
b10011001 !
0#
#18000
b10100111010110 '
1#
#19000
0#
#20000
1#
#21000
b100 $
b11110011 "
b100010 !
0#
#22000
b11010001 '
1#
#23000
0#
#24000
1#
#25000
b0 $
b1001001 "
b10111100 !
0#
#26000
b100000101 '
1#
#27000
0#
#28000
1#
#29000
b100 $
b1011 "
b11011000 !
0#
#30000
b11010011 '
1#
#31000
0#
#32000
1#
#33000
b10 $
b10011111 "
b1011 !
0#
#34000
b1011 '
1#
#35000
0#
#36000
1#
#37000
b11001100 "
b101110 !
0#
#38000
b1100 '
1#
#39000
0#
#40000
1#
#41000
b100 $
b10111101 "
b101011 !
0#
#42000
b10010110 '
1#
#43000
0#
#44000
1#
#45000
b0 $
b1011100 "
b1100100 !
0#
#46000
b11000000 '
1#
#47000
0#
#48000
1#
#49000
b101 $
b110100 "
b11010 !
0#
#50000
b11100101 '
1#
#51000
0#
#52000
1#
#53000
b10 $
b11001101 "
b10101011 !
0#
#54000
b10001001 '
1#
#55000
0#
#56000
1#
#57000
b1 $
b1001011 "
b10000110 !
0#
#58000
b10011101000010 '
1#
#59000
0#
#60000
1#
#61000
b100 $
b1110100 "
b10111010 !
0#
#62000
b11001110 '
1#
#63000
0#
#64000
1#
#65000
b1 $
b10101110 "
b10110100 !
0#
#66000
b111101001011000 '
1#
#67000
0#
#68000
1#
#69000
b11 $
b11101101 "
b10101 !
0#
#70000
b11111101 '
1#
#71000
0#
#72000
1#
#73000
b101 $
b1001001 "
b11010011 !
0#
#74000
b101100 '
1#
#75000
0#
#76000
1#
#77000
b10011111 "
b1111101 !
0#
#78000
b10000010 '
1#
#79000
0#
#80000
1#
#81000
b1101001 "
b110 !
0#
#82000
b11111001 '
1#
#83000
0#
#84000
1#
#85000
b100 $
b10011011 "
b11101000 !
0#
#86000
b1110011 '
1#
#87000
0#
#88000
1#
#89000
b10 $
b10111001 "
b11101 !
0#
#90000
b11001 '
1#
#91000
0#
#92000
1#
#93000
b11 $
b11110110 "
b11001001 !
0#
#94000
b11111111 '
1#
#95000
0#
#96000
1#
#97000
b10110 "
b1011 !
0#
#98000
b11111 '
1#
#99000
0#
#100000
1#
#101000
b0 $
b1111111 "
b11101 !
0#
#102000
b10011100 '
1#
#103000
0#
#104000
1#
#105000
b11000000 "
b11000110 !
0#
#106000
b110000110 '
1#
#107000
0#
#108000
1#
#109000
b1 $
b11011010 "
b10011110 !
0#
#110000
b1000011010001100 '
1#
#111000
0#
#112000
1#
#113000
b101 $
b1101001 "
b10101011 !
0#
#114000
b1010100 '
1#
#115000
0#
#116000
1#
#117000
b111011 "
b10000001 !
0#
#118000
b1111110 '
1#
#119000
0#
#120000
1#
#121000
b100 $
b10011111 "
b1100001 !
0#
#122000
b11111110 '
1#
#123000
0#
#124000
1#
#125000
b0 $
b11010001 "
b10000111 !
0#
#126000
b101011000 '
1#
#127000
0#
#128000
1#
#129000
b100 $
b10000101 "
b1011010 !
0#
#130000
b11011111 '
1#
#131000
0#
#132000
1#
#133000
b11 $
b10010100 "
b1100101 !
0#
#134000
b11110101 '
1#
#135000
0#
#136000
1#
#137000
b101 $
b11001010 "
b111000 !
0#
#138000
b11000111 '
1#
#139000
0#
#140000
1#
#141000
b1 $
b10011011 "
b11111111 !
0#
#142000
b1001101001100101 '
1#
#143000
0#
#144000
1#
#145000
b100 $
b1001111 "
b1110000 !
0#
#146000
b111111 '
1#
#147000
0#
#148000
1#
#149000
b0 $
b10001011 "
b10001100 !
0#
#150000
b100010111 '
1#
#151000
0#
#152000
1#
#153000
b11 $
b10111011 "
b1111010 !
0#
#154000
b11111011 '
1#
#155000
0#
#156000
1#
#157000
b0 $
b110001 "
b11010011 !
0#
#158000
b100000100 '
1#
#159000
0#
#160000
1#
#161000
b101 $
b11001001 "
b10011010 !
0#
#162000
b1100101 '
1#
#163000
0#
#164000
1#
#165000
b1100 "
b1101000 !
0#
#166000
b10010111 '
1#
#167000
0#
#168000
1#
#169000
b0 "
b1101001 !
0#
#170000
b10010110 '
1#
#171000
0#
#172000
1#
#173000
b11 $
b10110110 "
b10100111 !
0#
#174000
b10110111 '
1#
#175000
0#
#176000
1#
#177000
b111110 "
b11111101 !
0#
#178000
b11111111 '
1#
#179000
0#
#180000
1#
#181000
b0 $
b1111001 "
b1 !
0#
#182000
b1111010 '
1#
#183000
0#
#184000
1#
#185000
b11 $
b11000010 "
b1110000 !
0#
#186000
b11110010 '
1#
#187000
0#
#188000
1#
#189000
b0 $
b110010 "
b11100110 !
0#
#190000
b100011000 '
1#
#191000
0#
#192000
1#
#193000
b11 $
b110001 "
b11101011 !
0#
#194000
b11111011 '
1#
#195000
0#
#196000
1#
#197000
b0 $
b10110000 "
b111001 !
0#
#198000
b11101001 '
1#
#199000
0#
#200000
1#
#201000
b100 $
b11010111 "
b10010110 !
0#
#202000
b1000001 '
1#
#203000
0#
#204000
1#
#205000
0%
0#
